chem_templates/__init__.py
chem_templates/_modidx.py
chem_templates/assembly.py
chem_templates/building_blocks.py
chem_templates/chem.py
chem_templates/filter.py
chem_templates/fragments.py
chem_templates/imports.py
chem_templates/utils.py
chem_templates/synt_on/__init__.py
chem_templates/synt_on/config/BB_Marks.xml
chem_templates/synt_on/config/SMARTSLibNew.json
chem_templates/synt_on/fusion_reactions/Alkylation_arylation_of_NH-heterocycles.json
chem_templates/synt_on/fusion_reactions/Alkylation_arylation_of_NH-lactam.json
chem_templates/synt_on/fusion_reactions/Amine_alkylation_arylation.json
chem_templates/synt_on/fusion_reactions/Amine_sulphoacylation.json
chem_templates/synt_on/fusion_reactions/C-C couplings.json
chem_templates/synt_on/fusion_reactions/Condensation_of_Y-NH2_with_carbonyl_compounds.json
chem_templates/synt_on/fusion_reactions/Metal organics C-C bong assembling.json
chem_templates/synt_on/fusion_reactions/N-acylation.json
chem_templates/synt_on/fusion_reactions/O-acylation.json
chem_templates/synt_on/fusion_reactions/O-alkylation_arylation.json
chem_templates/synt_on/fusion_reactions/Olefination.json
chem_templates/synt_on/fusion_reactions/Radical_reactions.json
chem_templates/synt_on/fusion_reactions/S-alkylation_arylation.json
chem_templates/synt_on/src/SyntOn_BBs.py
chem_templates/synt_on/src/SyntOn_Classifier.py
chem_templates/synt_on/src/UsefulFunctions.py
chem_templates/synt_on/src/__init__.py
chem_templates-0.0.7.dist-info/LICENSE
chem_templates-0.0.7.dist-info/METADATA
chem_templates-0.0.7.dist-info/WHEEL
chem_templates-0.0.7.dist-info/entry_points.txt
chem_templates-0.0.7.dist-info/top_level.txt
chem_templates-0.0.7.dist-info/RECORD
