Metadata-Version: 2.1
Name: chem-templates
Version: 0.0.7
Summary: A python library for controlling chemical space
Home-page: https://github.com/DarkMatterAI/chem_templates
Author: Karl Heyer
Author-email: karl@darkmatterai.co
License: Apache Software License 2.0
Keywords: nbdev jupyter notebook python
Classifier: Development Status :: 4 - Beta
Classifier: Intended Audience :: Developers
Classifier: Natural Language :: English
Classifier: Programming Language :: Python :: 3.7
Classifier: Programming Language :: Python :: 3.8
Classifier: Programming Language :: Python :: 3.9
Classifier: Programming Language :: Python :: 3.10
Classifier: License :: OSI Approved :: Apache Software License
Requires-Python: >=3.7
License-File: LICENSE
Requires-Dist: rdkit
Requires-Dist: pandas
Provides-Extra: dev
